{
  "settings": {
    "index.refresh_interval": "30s",
    "number_of_shards": "1",
    "number_of_replicas": "0",
    "analysis": {
      "filter": {
        "english_stop": {
          "type":       "stop",
          "stopwords":  "_english_" 
        },
        "english_stemmer": {
          "type":       "stemmer",
          "language":   "english"
        },
        "english_possessive_stemmer": {
          "type":       "stemmer",
          "language":   "possessive_english"
        }
      },
      "analyzer": {
        "default": {
          "tokenizer":  "standard",
          "filter": [
            "english_possessive_stemmer",
            "lowercase",
            "english_stop",
            "english_stemmer"
          ]
        }
      }
    }
  },
  "mappings": {
    "properties" : {
      "accessories" : {
        "type" : "text",
        "fields" : {
          "keyword" : {
            "type" : "keyword",
            "ignore_above" : 256
          }
        }
      },
      "active" : {
        "type" : "boolean"
      },
      "bestBuyItemId" : {
        "type" : "keyword"
      },
      "bestSellingRank" : {
        "type" : "integer"
      },
      "categoryLeaf" : {
        "type" : "keyword"
      },
      "categoryPath" : {
        "type" : "text",
        "fields" : {
          "keyword" : {
            "type" : "keyword",
            "ignore_above" : 256
          }
        }
      },
      "categoryPathCount" : {
        "type" : "text",
        "fields" : {
          "keyword" : {
            "type" : "keyword",
            "ignore_above" : 256
          }
        }
      },
      "categoryPathIds" : {
        "type" : "text",
        "fields" : {
          "keyword" : {
            "type" : "keyword",
            "ignore_above" : 256
          }
        }
      },
      "class" : {
        "type" : "text",
        "fields" : {
          "keyword" : {
            "type" : "keyword",
            "ignore_above" : 256
          }
        }
      },
      "classId" : {
        "type" : "keyword"
      },
      "color" : {
        "type" : "text",
        "fields" : {
          "keyword" : {
            "type" : "keyword",
            "ignore_above" : 256
          }
        }
      },
      "condition" : {
        "type" : "text",
        "fields" : {
          "keyword" : {
            "type" : "keyword",
            "ignore_above" : 256
          }
        }
      },
      "customerReviewAverage" : {
        "type" : "double"
      },
      "customerReviewCount" : {
        "type" : "integer"
      },
      "department" : {
        "type" : "keyword"
      },
      "departmentId" : {
        "type" : "keyword"
      },
      "depth" : {
        "type" : "keyword"
      },
      "digital" : {
        "type" : "text",
        "fields" : {
          "keyword" : {
            "type" : "keyword",
            "ignore_above" : 256
          }
        }
      },
      "features" : {
        "type" : "text",
        "fields" : {
          "keyword" : {
            "type" : "keyword",
            "ignore_above" : 256
          }
        }
      },
      "frequentlyPurchasedWith" : {
        "type" : "text",
        "fields" : {
          "keyword" : {
            "type" : "keyword",
            "ignore_above" : 256
          }
        }
      },
      "height" : {
        "type" : "text",
        "fields" : {
          "keyword" : {
            "type" : "keyword",
            "ignore_above" : 256
          }
        }
      },
      "homeDelivery" : {
        "type" : "text",
        "fields" : {
          "keyword" : {
            "type" : "keyword",
            "ignore_above" : 256
          }
        }
      },
      "image" : {
        "type" : "keyword"
      },
      "inStoreAvailability" : {
        "type" : "boolean"
      },
      "inStorePickup" : {
        "type" : "boolean"
      },
      "longDescription" : {
        "type" : "text",
        "fields" : {
          "keyword" : {
            "type" : "keyword",
            "ignore_above" : 256
          }
        }
      },
      "longDescriptionHtml" : {
        "type" : "text",
        "fields" : {
          "keyword" : {
            "type" : "keyword",
            "ignore_above" : 256
          }
        }
      },
      "manufacturer" : {
        "type" : "text",
        "fields" : {
          "keyword" : {
            "type" : "keyword",
            "ignore_above" : 256
          }
        }
      },
      "modelNumber" : {
        "type" : "text",
        "fields" : {
          "keyword" : {
            "type" : "keyword",
            "ignore_above" : 256
          }
        }
      },
      "name" : {
        "type" : "text",
        "fields" : {
          "keyword" : {
            "type" : "keyword",
            "ignore_above" : 256
          }
        }
      },
      "onSale" : {
        "type" : "boolean"
      },
      "onlineAvailability" : {
        "type" : "boolean"
      },
      "productId" : {
        "type" : "keyword"
      },
      "quantityLimit" : {
        "type" : "integer"
      },
      "regularPrice" : {
        "type" : "double"
      },
      "relatedProducts" : {
        "type" : "text",
        "fields" : {
          "keyword" : {
            "type" : "keyword",
            "ignore_above" : 256
          }
        }
      },
      "releaseDate" : {
        "type" : "date"
      },
      "salePrice" : {
        "type" : "double"
      },
      "salesRankLongTerm" : {
        "type" : "integer"
      },
      "salesRankMediumTerm" :  {
        "type" : "integer"
      },
      "salesRankShortTerm" :  {
        "type" : "integer"
      },
      "shippingCost" : {
        "type" : "double"
      },
      "shippingWeight" : {
        "type" : "double"
      },
      "shortDescription" : {
        "type" : "text",
        "fields" : {
          "keyword" : {
            "type" : "keyword",
            "ignore_above" : 256
          }
        }
      },
      "shortDescriptionHtml" : {
        "type" : "text",
        "fields" : {
          "keyword" : {
            "type" : "keyword",
            "ignore_above" : 256
          }
        }
      },
      "sku" : {
        "type" : "keyword"
      },
      "startDate" : {
        "type" : "date"
      },
      "subclass" : {
        "type" : "text",
        "fields" : {
          "keyword" : {
            "type" : "keyword",
            "ignore_above" : 256
          }
        }
      },
      "subclassId" :{
        "type" : "keyword"
      },
      "tags" : {
        "type" : "text",
        "fields" : {
          "keyword" : {
            "type" : "keyword",
            "ignore_above" : 256
          }
        }
      },
      "type" : {
        "type" : "keyword"
      },
      "url" : {
        "type" : "keyword"
      },
      "weight" : {
        "type" : "keyword"
      },
      "width" : {
        "type" : "keyword"
      }
    }
  }
}